setup.py
olhovivo/__init__.py
olhovivo/api.py
olhovivo/utils.py
olhovivo.egg-info/PKG-INFO
olhovivo.egg-info/SOURCES.txt
olhovivo.egg-info/dependency_links.txt
olhovivo.egg-info/requires.txt
olhovivo.egg-info/top_level.txt
olhovivo/models/__init__.py
olhovivo/models/base.py
olhovivo/models/corredor.py
olhovivo/models/linha.py
olhovivo/models/parada.py
olhovivo/models/veiculo.py